{"id":101,"seatNumber":"Seat-1","booked":true},{"id":102,"seatNumber":"Seat-2","booked":false},{"id":103,"seatNumber":"Seat-3","booked":false},{"id":104,"seatNumber":"Seat-4","booked":false},{"id":105,"seatNumber":"Seat-5","booked":false},{"id":106,"seatNumber":"Seat-6","booked":false},{"id":107,"seatNumber":"Seat-7","booked":false},{"id":108,"seatNumber":"Seat-8","booked":false},{"id":109,"seatNumber":"Seat-9","booked":false},{"id":110,"seatNumber":"Seat-10","booked":false},{"id":111,"seatNumber":"Seat-11","booked":false},{"id":112,"seatNumber":"Seat-12","booked":false},{"id":113,"seatNumber":"Seat-13","booked":false},{"id":114,"seatNumber":"Seat-14","booked":false},{"id":115,"seatNumber":"Seat-15","booked":false},{"id":116,"seatNumber":"Seat-16","booked":false},{"id":117,"seatNumber":"Seat-17","booked":false},{"id":118,"seatNumber":"Seat-18","booked":false},{"id":119,"seatNumber":"Seat-19","booked":false},{"id":120,"seatNumber":"Seat-20","booked":false},{"id":121,"seatNumber":"Seat-21","booked":false},{"id":122,"seatNumber":"Seat-22","booked":false},{"id":123,"seatNumber":"Seat-23","booked":false},{"id":124,"seatNumber":"Seat-24","booked":false},{"id":125,"seatNumber":"Seat-25","booked":false},{"id":126,"seatNumber":"Seat-26","booked":false},{"id":127,"seatNumber":"Seat-27","booked":false},{"id":128,"seatNumber":"Seat-28","booked":false},{"id":129,"seatNumber":"Seat-29","booked":false},{"id":130,"seatNumber":"Seat-30","booked":false},{"id":131,"seatNumber":"Seat-31","booked":false},{"id":132,"seatNumber":"Seat-32","booked":false},{"id":133,"seatNumber":"Seat-33","booked":false},{"id":134,"seatNumber":"Seat-34","booked":false},{"id":135,"seatNumber":"Seat-35","booked":false},{"id":136,"seatNumber":"Seat-36","booked":false},{"id":137,"seatNumber":"Seat-37","booked":false},{"id":138,"seatNumber":"Seat-38","booked":false},{"id":139,"seatNumber":"Seat-39","booked":false},{"id":140,"seatNumber":"Seat-40","booked":false},{"id":141,"seatNumber":"Seat-41","booked":false},{"id":142,"seatNumber":"Seat-42","booked":false},{"id":143,"seatNumber":"Seat-43","booked":false},{"id":144,"seatNumber":"Seat-44","booked":false},{"id":145,"seatNumber":"Seat-45","booked":false},{"id":146,"seatNumber":"Seat-46","booked":false},{"id":147,"seatNumber":"Seat-47","booked":false},{"id":148,"seatNumber":"Seat-48","booked":false},{"id":149,"seatNumber":"Seat-49","booked":false},{"id":150,"seatNumber":"Seat-50","booked":false},{"id":151,"seatNumber":"Seat-51","booked":false},{"id":152,"seatNumber":"Seat-52","booked":false},{"id":153,"seatNumber":"Seat-53","booked":false},{"id":154,"seatNumber":"Seat-54","booked":false},{"id":155,"seatNumber":"Seat-55","booked":false},{"id":156,"seatNumber":"Seat-56","booked":false},{"id":157,"seatNumber":"Seat-57","booked":false},{"id":158,"seatNumber":"Seat-58","booked":false},{"id":159,"seatNumber":"Seat-59","booked":false},{"id":160,"seatNumber":"Seat-60","booked":false},{"id":161,"seatNumber":"Seat-61","booked":false},{"id":162,"seatNumber":"Seat-62","booked":false},{"id":163,"seatNumber":"Seat-63","booked":false},{"id":164,"seatNumber":"Seat-64","booked":false},{"id":165,"seatNumber":"Seat-65","booked":false},{"id":166,"seatNumber":"Seat-66","booked":false},{"id":167,"seatNumber":"Seat-67","booked":false},{"id":168,"seatNumber":"Seat-68","booked":false},{"id":169,"seatNumber":"Seat-69","booked":false},{"id":170,"seatNumber":"Seat-70","booked":false},{"id":171,"seatNumber":"Seat-71","booked":false},{"id":172,"seatNumber":"Seat-72","booked":false},{"id":173,"seatNumber":"Seat-73","booked":false},{"id":174,"seatNumber":"Seat-74","booked":false},{"id":175,"seatNumber":"Seat-75","booked":false},{"id":176,"seatNumber":"Seat-76","booked":false},{"id":177,"seatNumber":"Seat-77","booked":false},{"id":178,"seatNumber":"Seat-78","booked":false},{"id":179,"seatNumber":"Seat-79","booked":false},{"id":180,"seatNumber":"Seat-80","booked":false},{"id":181,"seatNumber":"Seat-81","booked":false},{"id":182,"seatNumber":"Seat-82","booked":false},{"id":183,"seatNumber":"Seat-83","booked":false},{"id":184,"seatNumber":"Seat-84","booked":false},{"id":185,"seatNumber":"Seat-85","booked":false},{"id":186,"seatNumber":"Seat-86","booked":false},{"id":187,"seatNumber":"Seat-87","booked":false},{"id":188,"seatNumber":"Seat-88","booked":false},{"id":189,"seatNumber":"Seat-89","booked":false},{"id":190,"seatNumber":"Seat-90","booked":false},{"id":191,"seatNumber":"Seat-91","booked":false},{"id":192,"seatNumber":"Seat-92","booked":false},{"id":193,"seatNumber":"Seat-93","booked":false},{"id":194,"seatNumber":"Seat-94","booked":false},{"id":195,"seatNumber":"Seat-95","booked":false},{"id":196,"seatNumber":"Seat-96","booked":false},{"id":197,"seatNumber":"Seat-97","booked":false},{"id":198,"seatNumber":"Seat-98","booked":false},{"id":199,"seatNumber":"Seat-99","booked":false},{"id":200,"seatNumber":"Seat-100","booked":false}]